hdx/utilities/__init__.py
hdx/utilities/_version.py
hdx/utilities/base_downloader.py
hdx/utilities/compare.py
hdx/utilities/dateparse.py
hdx/utilities/dictandlist.py
hdx/utilities/downloader.py
hdx/utilities/easy_logging.py
hdx/utilities/email.py
hdx/utilities/encoding.py
hdx/utilities/error_handler.py
hdx/utilities/errors_onexit.py
hdx/utilities/file_hashing.py
hdx/utilities/frictionless_wrapper.py
hdx/utilities/html.py
hdx/utilities/loader.py
hdx/utilities/matching.py
hdx/utilities/path.py
hdx/utilities/retriever.py
hdx/utilities/saver.py
hdx/utilities/session.py
hdx/utilities/state.py
hdx/utilities/text.py
hdx/utilities/url.py
hdx/utilities/useragent.py
hdx/utilities/uuid.py
hdx/utilities/zip_crc.py
hdx_python_utilities-4.0.4.dist-info/METADATA
hdx_python_utilities-4.0.4.dist-info/WHEEL
hdx_python_utilities-4.0.4.dist-info/licenses/LICENSE
hdx_python_utilities-4.0.4.dist-info/RECORD
