Metadata-Version: 2.4
Name: hdx-python-utilities
Version: 4.0.4
Summary: HDX Python Utilities for streaming tabular data, date and time handling and other helpful functions
Project-URL: Homepage, https://github.com/OCHA-DAP/hdx-python-utilities
Author-email: Michael Rans <rans@email.com>
License: MIT
License-File: LICENSE
Keywords: HDX,date,datetime,dict,json,library,list,streaming,tabular data,time,timezone,utilities,yaml
Classifier: Development Status :: 5 - Production/Stable
Classifier: Intended Audience :: Developers
Classifier: License :: OSI Approved :: MIT License
Classifier: Natural Language :: English
Classifier: Operating System :: MacOS
Classifier: Operating System :: Microsoft :: Windows
Classifier: Operating System :: POSIX :: Linux
Classifier: Operating System :: Unix
Classifier: Programming Language :: Python
Classifier: Programming Language :: Python :: 3
Classifier: Programming Language :: Python :: 3 :: Only
Classifier: Programming Language :: Python :: 3.10
Classifier: Programming Language :: Python :: 3.11
Classifier: Programming Language :: Python :: 3.12
Classifier: Programming Language :: Python :: 3.13
Classifier: Programming Language :: Python :: 3.14
Classifier: Topic :: Software Development :: Libraries :: Python Modules
Requires-Python: >=3.10
Requires-Dist: frictionless>=5.18.0
Requires-Dist: ijson>=3.2.3
Requires-Dist: jsonlines>=4.0.0
Requires-Dist: loguru
Requires-Dist: openpyxl>=3.1.2
Requires-Dist: pyphonetics
Requires-Dist: python-dateutil<2.9.1,>=2.9.0
Requires-Dist: ratelimit
Requires-Dist: requests-file
Requires-Dist: ruamel-yaml
Requires-Dist: tableschema-to-template>=0.0.13
Requires-Dist: typing-extensions
Requires-Dist: xlrd>=2.0.1
Requires-Dist: xlsx2csv
Requires-Dist: xlwt>=1.3.0
Provides-Extra: diff
Requires-Dist: cydifflib; extra == 'diff'
Provides-Extra: docs
Requires-Dist: mkapi; extra == 'docs'
Provides-Extra: email
Requires-Dist: email-validator; extra == 'email'
Provides-Extra: html
Requires-Dist: beautifulsoup4; extra == 'html'
Requires-Dist: html5lib; extra == 'html'
